gsifpytools/__init__.py
gsifpytools/gsifpytools.py
gsif_pytools-0.0.5.dist-info/LICENSE
gsif_pytools-0.0.5.dist-info/METADATA
gsif_pytools-0.0.5.dist-info/WHEEL
gsif_pytools-0.0.5.dist-info/top_level.txt
gsif_pytools-0.0.5.dist-info/RECORD
