Metadata-Version: 2.1
Name: gsif-pytools
Version: 0.0.5
Summary: A package with tools to aid Gator Student Investment Fund Portfolio Attribution Specialists.
Home-page: https://github.com/gsifpytools/homepage/
Author: Mingyin Zhu
Author-email: mzhu0114@gmail.com
License: UNKNOWN
Platform: UNKNOWN
Classifier: Programming Language :: Python :: 3.10
Classifier: License :: OSI Approved :: MIT License
Requires-Dist: pandas
Requires-Dist: numpy
Requires-Dist: requests (>=2)
Requires-Dist: openpyxl (>=3)
Requires-Dist: pytesseract (>=0.3.9)
Requires-Dist: opencv-python (>=4)
Requires-Dist: pdf2image (>=1)
